flowcheck/__init__.py
flowcheck/analyzer.py
flowcheck/cli.py
flowcheck/models.py
flowcheck/reason.py
py_flow_check-1.0.0.dist-info/METADATA
py_flow_check-1.0.0.dist-info/WHEEL
py_flow_check-1.0.0.dist-info/entry_points.txt
py_flow_check-1.0.0.dist-info/top_level.txt
py_flow_check-1.0.0.dist-info/RECORD
