Metadata-Version: 2.4
Name: py-flow-check
Version: 1.0.0
Summary: Detect logical flow bugs in Python code using static analysis
Author: Sourav Parija
License-Expression: MIT
Requires-Python: >=3.9
